{
  "books": [
    {
      "id": "1",
      "name": "Raspberry Pi User Guide",
      "cover": "http://url.to.book.cover",
      "pages": "221",
      "published": "2012",
      "isbn": "9781118464465",
      "author": "Eben Upton",
      "userId": "1",
      "userEmail": "Felix IT solitions"
    },
    {
      "obj": {
        "name": "Some Storydsfdf",
        "cover": "https::/some-story/book",
        "pages": "201",
        "published": "2023",
        "isbn": "1546546876545",
        "author": "Somebody that I used to know"
      },
      "name": "Some Story for children",
      "cover": "https://some-story/book",
      "pages": "201",
      "published": "2023",
      "isbn": "1546546876545",
      "author": "Somebody",
      "id": "849946cc-5dac-466b-ba35-bfc0c9c59f38",
      "userId": "YyKYpZ1nnCMisLSkY683LdoPRQ83",
      "userEmail": "dilshodjonmahmudov30@gmail.com"
    },
    {
      "id": "a862d4a1-c02d-4b64-a889-18ad7b72d30f",
      "name": "Interesting book",
      "cover": "https://interesting.com/",
      "pages": "158",
      "published": "2024",
      "isbn": "5465132654",
      "author": "John Doe",
      "userId": "YyKYpZ1nnCMisLSkY683LdoPRQ83",
      "userEmail": "dilshodjonmahmudov30@gmail.com"
    },
    {
      "id": "817527ed-b0dc-47ea-93f4-100af1d1aac0",
      "name": "sfsd",
      "cover": "fsgfg",
      "pages": "45",
      "published": "2014",
      "isbn": "14497944644",
      "author": "gsgdfgsfgffsfgsfgs",
      "userId": "3ba038ec-4821-43fa-b0bf-abc536572356",
      "userEmail": null
    },
    {
      "id": "714d0293-bfd8-4735-b29c-f4233f854c4f",
      "name": "sdfgsd",
      "cover": "fdsgdfg",
      "pages": "45",
      "published": "2013",
      "isbn": "5465412",
      "author": "gfdgsdgsdg",
      "userId": "3ba038ec-4821-43fa-b0bf-abc536572356",
      "userEmail": null
    }
  ],
  "signup": [
    {
      "id": "8c5b6f62-b9b3-4620-85fe-bdb966f1a9e0",
      "userId": "3ba038ec-4821-43fa-b0bf-abc536572356",
      "username": "g",
      "password": "g"
    },
    {
      "id": "63955152-fa6b-4bfb-97f4-4a603704d82c",
      "userId": "eccd1288-852e-49d0-9591-6502639d6a06",
      "username": "Dilshod0156",
      "password": "dilshod0156"
    },
    {
      "id": "c598a7c0-b159-49f4-997c-d84609a6e618",
      "userId": "e6873616-5aba-4a76-a5ca-3b048882d086",
      "username": "dm0156",
      "password": "dilshod0156"
    }
  ]
}